ticsummary_domain/__init__.py
ticsummary_domain/__main__.py
ticsummary_domain/backWorking.py
ticsummary_domain/dataTIC.py
ticsummary_domain/databaseMYSQL.py
ticsummary_domain/debugMode.py
ticsummary_domain/inputDataHandler.py
ticsummary_domain/loaderData.py
ticsummary_domain/modeShowData.py
ticsummary_domain/model.py
ticsummary_domain/outputDataHandler.py
ticsummary_domain/thread.py
ticsummary_domain/ui/__init__.py
ticsummary_domain/ui/chooseRecordDialog.py
ticsummary_domain/ui/connectionConfigurationDialog.py
ticsummary_domain/ui/counterDock.py
ticsummary_domain/ui/descriptionDataDock.py
ticsummary_domain/ui/mainWindow.py
ticsummary_domain/ui/openSqlDataDialog.py
ticsummary_domain/ui/profileBeamDock.py
ticsummary_domain/ui/settingsColorBarDialog.py
ticsummary_domain/ui/viewGraphicsDialog.py
ticsummary_domain/ui/images/CET-C1.jpg
ticsummary_domain/ui/images/CET-C1s.jpg
ticsummary_domain/ui/images/CET-C2.jpg
ticsummary_domain/ui/images/CET-C2s.jpg
ticsummary_domain/ui/images/CET-C3.jpg
ticsummary_domain/ui/images/CET-C3s.jpg
ticsummary_domain/ui/images/CET-C4.jpg
ticsummary_domain/ui/images/CET-C4s.jpg
ticsummary_domain/ui/images/CET-C5.jpg
ticsummary_domain/ui/images/CET-C5s.jpg
ticsummary_domain/ui/images/CET-C6.jpg
ticsummary_domain/ui/images/CET-C6s.jpg
ticsummary_domain/ui/images/CET-C7.jpg
ticsummary_domain/ui/images/CET-C7s.jpg
ticsummary_domain/ui/images/CET-CBL1.jpg
ticsummary_domain/ui/images/CET-CBL2.jpg
ticsummary_domain/ui/images/CET-CBTL1.jpg
ticsummary_domain/ui/images/CET-CBTL2.jpg
ticsummary_domain/ui/images/CET-D1.jpg
ticsummary_domain/ui/images/CET-D1A.jpg
ticsummary_domain/ui/images/CET-D2.jpg
ticsummary_domain/ui/images/CET-D3.jpg
ticsummary_domain/ui/images/CET-D4.jpg
ticsummary_domain/ui/images/CET-D6.jpg
ticsummary_domain/ui/images/CET-D7.jpg
ticsummary_domain/ui/images/CET-D8.jpg
ticsummary_domain/ui/images/CET-I1.jpg
ticsummary_domain/ui/images/CET-I2.jpg
ticsummary_domain/ui/images/CET-I3.jpg
ticsummary_domain/ui/images/CET-L1.jpg
neofti_ticsummary_domain-1.2.20.dist-info/METADATA
neofti_ticsummary_domain-1.2.20.dist-info/WHEEL
neofti_ticsummary_domain-1.2.20.dist-info/top_level.txt
neofti_ticsummary_domain-1.2.20.dist-info/RECORD
