Metadata-Version: 2.1
Name: neofti_ticsummary_domain
Version: 1.2.20
Summary: TIC data viewer domain
Home-page: 
Author: DmitryKorovkin
Author-email: d.korovkin69@gmail.com
Classifier: Programming Language :: Python :: 3
Classifier: License :: OSI Approved :: MIT License
Classifier: Operating System :: OS Independent
Requires-Dist: pyqtgraph
Requires-Dist: numpy
Requires-Dist: pyqt6
Requires-Dist: mysql-connector-python
Requires-Dist: matplotlib
Requires-Dist: numba
